smartdebug/__init__.py
smartdebug/decorators.py
smartdebug/help_utils.py
smartdebug/log_utils.py
smartdebug/trace_utils.py
smartdebug/watch_utils.py
smartdebug-0.2.0.dist-info/METADATA
smartdebug-0.2.0.dist-info/WHEEL
smartdebug-0.2.0.dist-info/top_level.txt
smartdebug-0.2.0.dist-info/RECORD
